nonebot_plugin_better_broadcast/__init__.py
nonebot_plugin_better_broadcast/config.py
nonebot_plugin_better_broadcast-1.0.6.dist-info/LICENSE
nonebot_plugin_better_broadcast-1.0.6.dist-info/WHEEL
nonebot_plugin_better_broadcast-1.0.6.dist-info/METADATA
nonebot_plugin_better_broadcast-1.0.6.dist-info/RECORD
