Metadata-Version: 2.1
Name: nonebot-plugin-better-broadcast
Version: 1.0.6
Summary: nonebot2 plugin, boardcast your message to every groups
Home-page: https://github.com/captain-wangrun-cn/nonebot-plugin-better-broadcast
License: GPL-3.0
Author: WR
Author-email: wangrun114514@foxmail.com
Requires-Python: >=3.9,<4.0
Classifier: License :: OSI Approved :: GNU General Public License v3 (GPLv3)
Classifier: Programming Language :: Python :: 3
Classifier: Programming Language :: Python :: 3.10
Classifier: Programming Language :: Python :: 3.9
Requires-Dist: nonebot-adapter-onebot (>=2.0.0,<3.0.0)
Requires-Dist: nonebot-plugin-waiter (==0.8.0)
Requires-Dist: nonebot2 (>=2.2.0,<3.0.0)
Project-URL: Repository, https://github.com/captain-wangrun-cn/nonebot-plugin-better-broadcast
